hello_name/__init__.py
hello_name/_nbdev.py
hello_name/core.py
hello_name-0.0.2.dist-info/LICENSE
hello_name-0.0.2.dist-info/METADATA
hello_name-0.0.2.dist-info/WHEEL
hello_name-0.0.2.dist-info/entry_points.txt
hello_name-0.0.2.dist-info/top_level.txt
hello_name-0.0.2.dist-info/RECORD
